sbx_freeling/__init__.py
sbx_freeling/freeling.py
sbx_freeling/models.py
sparv_sbx_freeling-5.2.0.dist-info/LICENSE
sparv_sbx_freeling-5.2.0.dist-info/METADATA
sparv_sbx_freeling-5.2.0.dist-info/WHEEL
sparv_sbx_freeling-5.2.0.dist-info/entry_points.txt
sparv_sbx_freeling-5.2.0.dist-info/top_level.txt
sparv_sbx_freeling-5.2.0.dist-info/RECORD
