Metadata-Version: 2.1
Name: sparv-sbx-freeling
Version: 5.2.0
Summary: FreeLing plug-in for Sparv (Språkbanken's corpus annotation pipeline)
Home-page: https://github.com/spraakbanken/sparv-sbx-freeling/
Author: Språkbanken
Author-email: sb-info@svenska.gu.se
License: GNU GPL
Requires-Python: >=3.8
License-File: LICENSE
Requires-Dist: sparv-pipeline >=5.2.0
